oledump/__init__.py
oledump/__main__.py
oledump-0.0.0.dist-info/LICENSE
oledump-0.0.0.dist-info/METADATA
oledump-0.0.0.dist-info/WHEEL
oledump-0.0.0.dist-info/top_level.txt
oledump-0.0.0.dist-info/RECORD
