Metadata-Version: 2.2
Name: oledump
Version: 0.0.0
Summary: oledump ready to use and cli optimized. A fork of https://blog.didierstevens.com/programs/oledump-py/
Author-email: Juan Cerezo <jcerezo.dev@proton.me>
License: This is free and unencumbered software released into the public domain.
Classifier: Programming Language :: Python :: 3
Requires-Python: >=3.12
License-File: LICENSE
Provides-Extra: test
Requires-Dist: pytest; extra == "test"
Provides-Extra: lint
Requires-Dist: black; extra == "lint"
Requires-Dist: pylint; extra == "lint"
Requires-Dist: pyright; extra == "lint"
Requires-Dist: isort; extra == "lint"
Requires-Dist: autoflake; extra == "lint"
Requires-Dist: radon; extra == "lint"
Provides-Extra: dev
Requires-Dist: pre-commit; extra == "dev"
Requires-Dist: oledump[test]; extra == "dev"
Requires-Dist: oledump[lint]; extra == "dev"
Provides-Extra: ci
Requires-Dist: pre-commit; extra == "ci"
Requires-Dist: oledump[test]; extra == "ci"
Requires-Dist: oledump[lint]; extra == "ci"
